auto_changelog/__init__.py
auto_changelog/__main__.py
auto_changelog/domain_model.py
auto_changelog/presenter.py
auto_changelog/repository.py
auto_changelog/templates/compact.jinja2
auto_changelog/templates/macros.jinja2
auto_changelog-0.6.0.dist-info/entry_points.txt
auto_changelog-0.6.0.dist-info/LICENSE
auto_changelog-0.6.0.dist-info/WHEEL
auto_changelog-0.6.0.dist-info/METADATA
auto_changelog-0.6.0.dist-info/RECORD
