Metadata-Version: 2.1
Name: auto-changelog
Version: 0.6.0
Summary: Simple tool to generate nice, formatted changelogs from vcs
Home-page: https://github.com/Michael-F-Bryan/auto-changelog
License: MIT
Keywords: git,changelog
Author: Michael F Bryan
Author-email: michaelfbryan@gmail.com
Requires-Python: >=3.7.2
Classifier: Development Status :: 4 - Beta
Classifier: Environment :: Console
Classifier: Intended Audience :: Developers
Classifier: License :: OSI Approved :: MIT License
Classifier: Operating System :: POSIX :: Linux
Classifier: Programming Language :: Python :: 3
Classifier: Programming Language :: Python :: 3.8
Classifier: Programming Language :: Python :: 3.9
Classifier: Programming Language :: Python :: 3.10
Classifier: Programming Language :: Python :: 3.11
Classifier: Programming Language :: Python :: 3
Classifier: Programming Language :: Python :: 3.7
Classifier: Programming Language :: Python :: 3.8
Classifier: Programming Language :: Python :: 3.9
Classifier: Topic :: Software Development :: Build Tools
Classifier: Topic :: Software Development :: Documentation
Requires-Dist: Click (>=8.0)
Requires-Dist: docopt (>=0.6.2)
Requires-Dist: gitpython (>=2.1)
Requires-Dist: jinja2 (>=3.0)
Project-URL: Repository, https://github.com/Michael-F-Bryan/auto-changelog
